Workbook

Sheet Instructions
A1: Bookkeeping Ledger — QuickBooks-ready
A2: Built by the GEAUX AI team (finance seat: schema & controls). Import this file into Google Sheets and connect the agent.
A4: THE ONE RULE
A5: Nothing posts to QuickBooks until a human sets Status = Approved. This single gate keeps bad reads out and stops double-posting.
A7: WORKFLOW
A8: 1. Upload a bank statement, invoice, or check photo to the agent.
A9: 2. The agent extracts each transaction and adds a row with Status = Needs Review (blue columns).
A10: 3. You review: confirm the Account (yellow), fix anything wrong, and set Status = Approved. Check the Dup_Check column first.
A11: 4. The agent posts every Approved row to QuickBooks, writes back QBO_Txn_ID, and flips Status to Posted-QBO.
A12: 5. Weekly: open the Reconciliation tab and run the three-way tie-out.
A14: COLOR KEY
A15: Blue columns = the agent fills these automatically.
... A27: - Confidence below your threshold (suggested 90%) stays in Needs Review no matter what.

Sheet Transactions
A1: Txn_ID | B1: Date | C1: Payee/Vendor | D1: Amount | E1: Type | F1: Account (QBO) | G1: Class/Location | H1: Memo/Description | I1: Source_Doc_Link | J1: Source_Doc_Hash | K1: Bank Ref / Check# | L1: Status | M1: QBO_Txn_ID | N1: Confidence | O1: Entered_By | P1: Entered_Date | Q1: Dup_Check
A2: a1b2c3d4-0001 | B2: 2026-07-15 | C2: Office Depot | D2: 128.44 | E2: Expense | F2: Office Supplies | H2: Printer paper + toner (invoice #4471) | I2: https://drive.google.com/file/d/EXAMPLE | J2: 9f2c...e71a (sha256) | K2: CHK 1043 | L2: Needs Review | N2: 0.98 | O2: agent | P2: 2026-07-15 | Q2: =IF($J2="","",IF(COUNTIF($J$2:$J$2000,$J2)>1,"DUP-HASH",IF(COUNTIFS($B$2:$B$2000,$B2,$D$2:$D$2000,$D2,$C$2:$C$2000,$C2)>1,"DUP-MATCH","")))
Q3: =IF($J3="","",IF(COUNTIF($J$2:$J$2000,$J3)>1,"DUP-HASH",IF(COUNTIFS($B$2:$B$2000,$B3,$D$2:$D$2000,$D3,$C$2:$C$2000,$C3)>1,"DUP-MATCH","")))
Q4: =IF($J4="","",IF(COUNTIF($J$2:$J$2000,$J4)>1,"DUP-HASH",IF(COUNTIFS($B$2:$B$2000,$B4,$D$2:$D$2000,$D4,$C$2:$C$2000,$C4)>1,"DUP-MATCH","")))
Q5: =IF($J5="","",IF(COUNTIF($J$2:$J$2000,$J5)>1,"DUP-HASH",IF(COUNTIFS($B$2:$B$2000,$B5,$D$2:$D$2000,$D5,$C$2:$C$2000,$C5)>1,"DUP-MATCH","")))
Q6: =IF($J6="","",IF(COUNTIF($J$2:$J$2000,$J6)>1,"DUP-HASH",IF(COUNTIFS($B$2:$B$2000,$B6,$D$2:$D$2000,$D6,$C$2:$C$2000,$C6)>1,"DUP-MATCH","")))
Q7: =IF($J7="","",IF(COUNTIF($J$2:$J$2000,$J7)>1,"DUP-HASH",IF(COUNTIFS($B$2:$B$2000,$B7,$D$2:$D$2000,$D7,$C$2:$C$2000,$C7)>1,"DUP-MATCH","")))
Q8: =IF($J8="","",IF(COUNTIF($J$2:$J$2000,$J8)>1,"DUP-HASH",IF(COUNTIFS($B$2:$B$2000,$B8,$D$2:$D$2000,$D8,$C$2:$C$2000,$C8)>1,"DUP-MATCH","")))
Q9: =IF($J9="","",IF(COUNTIF($J$2:$J$2000,$J9)>1,"DUP-HASH",IF(COUNTIFS($B$2:$B$2000,$B9,$D$2:$D$2000,$D9,$C$2:$C$2000,$C9)>1,"DUP-MATCH","")))
Q10: =IF($J10="","",IF(COUNTIF($J$2:$J$2000,$J10)>1,"DUP-HASH",IF(COUNTIFS($B$2:$B$2000,$B10,$D$2:$D$2000,$D10,$C$2:$C$2000,$C10)>1,"DUP-MATCH","")))
Q11: =IF($J11="","",IF(COUNTIF($J$2:$J$2000,$J11)>1,"DUP-HASH",IF(COUNTIFS($B$2:$B$2000,$B11,$D$2:$D$2000,$D11,$C$2:$C$2000,$C11)>1,"DUP-MATCH","")))
Q12: =IF($J12="","",IF(COUNTIF($J$2:$J$2000,$J12)>1,"DUP-HASH",IF(COUNTIFS($B$2:$B$2000,$B12,$D$2:$D$2000,$D12,$C$2:$C$2000,$C12)>1,"DUP-MATCH","")))
Q13: =IF($J13="","",IF(COUNTIF($J$2:$J$2000,$J13)>1,"DUP-HASH",IF(COUNTIFS($B$2:$B$2000,$B13,$D$2:$D$2000,$D13,$C$2:$C$2000,$C13)>1,"DUP-MATCH","")))
Q14: =IF($J14="","",IF(COUNTIF($J$2:$J$2000,$J14)>1,"DUP-HASH",IF(COUNTIFS($B$2:$B$2000,$B14,$D$2:$D$2000,$D14,$C$2:$C$2000,$C14)>1,"DUP-MATCH","")))
... Q201: =IF($J201="","",IF(COUNTIF($J$2:$J$2000,$J201)>1,"DUP-HASH",IF(COUNTIFS($B$2:$B$2000,$B201,$D$2:$D$2000,$D201,$C$2:$C$2000,$C201)>1,"DUP-MATCH","")))

Sheet Vendor Map
A1: Vendor / Payee -> QuickBooks account mapping
A2: The agent checks this tab first. If a payee is here, it auto-fills the Account. If not, the row is forced to Needs Review.
A4: Payee/Vendor | B4: QBO Account (Category) | C4: Default Type | D4: Notes
A5: Office Depot | B5: Office Supplies | C5: Expense | D5: Example mapping — replace with your real vendors
A6: Comcast Business | B6: Utilities | C6: Expense
A7: Stripe Payout | B7: Sales Income | C7: Deposit | D7: Incoming revenue
A8: ADP | B8: Payroll Expenses | C8: Expense
A9: Shell | B9: Auto & Fuel | C9: Expense

Sheet Reconciliation
A1: Reconciliation & Controls
A2: Run the three-way tie-out weekly (with each new bank statement). Bank / QuickBooks totals in yellow are pulled by you from those systems.
A4: STATUS SUMMARY
A5: Needs Review | B5: =COUNTIF(Transactions!$L$2:$L$2000,"Needs Review")
A6: Approved (not yet posted) | B6: =COUNTIF(Transactions!$L$2:$L$2000,"Approved")
A7: Posted to QuickBooks | B7: =COUNTIF(Transactions!$L$2:$L$2000,"Posted-QBO")
A8: Rejected | B8: =COUNTIF(Transactions!$L$2:$L$2000,"Rejected")
A9: Duplicate flags to investigate | B9: =COUNTIF(Transactions!$Q$2:$Q$2000,"DUP-*")
A11: THREE-WAY TIE-OUT (this period)
A12: Posted deposits (Sheets) | B12: =SUMIFS(Transactions!$D$2:$D$2000,Transactions!$E$2:$E$2000,"Deposit",Transactions!$L$2:$L$2000,"Posted-QBO")
A13: Posted expenses (Sheets) | B13: =SUMIFS(Transactions!$D$2:$D$2000,Transactions!$E$2:$E$2000,"Expense",Transactions!$L$2:$L$2000,"Posted-QBO")
A14: Net change per Sheets | B14: =B12-B13
A15: Net change per Bank Statement | B15: 0 | C15: <- enter from the bank statement
A16: Net change per QuickBooks report | B16: 0 | C16: <- enter from a QuickBooks P&L / register
A18: Variance: Sheets vs Bank | B18: =B14-B15
A19: Variance: QuickBooks vs Sheets | B19: =B16-B14
A20: Result | B20: =IF(AND(ABS(B18)<0.005,ABS(B19)<0.005),"TIE - books match","INVESTIGATE - see variances")
